MANIFEST.in
README
requirements.txt
setup.py
ajenti.plugin.passwd.egg-info/PKG-INFO
ajenti.plugin.passwd.egg-info/SOURCES.txt
ajenti.plugin.passwd.egg-info/dependency_links.txt
ajenti.plugin.passwd.egg-info/requires.txt
ajenti.plugin.passwd.egg-info/top_level.txt
ajenti_plugin_passwd/README.md
ajenti_plugin_passwd/__init__.py
ajenti_plugin_passwd/bower.json
ajenti_plugin_passwd/plugin.yml
ajenti_plugin_passwd/requirements.txt
ajenti_plugin_passwd/views.py
ajenti_plugin_passwd/locale/app.pot
ajenti_plugin_passwd/locale/af/LC_MESSAGES/app.js
ajenti_plugin_passwd/locale/af/LC_MESSAGES/app.po
ajenti_plugin_passwd/locale/af/LC_MESSAGES/app.po~
ajenti_plugin_passwd/locale/ar/LC_MESSAGES/app.js
ajenti_plugin_passwd/locale/ar/LC_MESSAGES/app.po
ajenti_plugin_passwd/locale/ar/LC_MESSAGES/app.po~
ajenti_plugin_passwd/locale/be/LC_MESSAGES/app.js
ajenti_plugin_passwd/locale/be/LC_MESSAGES/app.po
ajenti_plugin_passwd/locale/be/LC_MESSAGES/app.po~
ajenti_plugin_passwd/locale/bg/LC_MESSAGES/app.js
ajenti_plugin_passwd/locale/bg/LC_MESSAGES/app.po
ajenti_plugin_passwd/locale/bg/LC_MESSAGES/app.po~
ajenti_plugin_passwd/locale/bn/LC_MESSAGES/app.js
ajenti_plugin_passwd/locale/bn/LC_MESSAGES/app.po
ajenti_plugin_passwd/locale/bn/LC_MESSAGES/app.po~
ajenti_plugin_passwd/locale/bs/LC_MESSAGES/app.js
ajenti_plugin_passwd/locale/bs/LC_MESSAGES/app.po
ajenti_plugin_passwd/locale/ca/LC_MESSAGES/app.js
ajenti_plugin_passwd/locale/ca/LC_MESSAGES/app.po
ajenti_plugin_passwd/locale/ca/LC_MESSAGES/app.po~
ajenti_plugin_passwd/locale/cs/LC_MESSAGES/app.js
ajenti_plugin_passwd/locale/cs/LC_MESSAGES/app.po
ajenti_plugin_passwd/locale/cs/LC_MESSAGES/app.po~
ajenti_plugin_passwd/locale/da/LC_MESSAGES/app.js
ajenti_plugin_passwd/locale/da/LC_MESSAGES/app.po
ajenti_plugin_passwd/locale/da/LC_MESSAGES/app.po~
ajenti_plugin_passwd/locale/de/LC_MESSAGES/app.js
ajenti_plugin_passwd/locale/de/LC_MESSAGES/app.po
ajenti_plugin_passwd/locale/de/LC_MESSAGES/app.po~
ajenti_plugin_passwd/locale/el/LC_MESSAGES/app.js
ajenti_plugin_passwd/locale/el/LC_MESSAGES/app.po
ajenti_plugin_passwd/locale/el/LC_MESSAGES/app.po~
ajenti_plugin_passwd/locale/en/LC_MESSAGES/app.po
ajenti_plugin_passwd/locale/eo/LC_MESSAGES/app.js
