Metadata-Version: 1.2
Name: ajenti.plugin.passwd
Version: 0.26
Summary: User DB API
Home-page: https://ajenti.org
Author: Ajenti project
Author-email: e@ajenti.org
License: UNKNOWN
Platform: UNKNOWN
Requires-Python: >=3
